pulumi_rancher2/__init__.py
pulumi_rancher2/_inputs.py
pulumi_rancher2/_utilities.py
pulumi_rancher2/app_v2.py
pulumi_rancher2/auth_config_active_directory.py
pulumi_rancher2/auth_config_adfs.py
pulumi_rancher2/auth_config_azure_ad.py
pulumi_rancher2/auth_config_free_ipa.py
pulumi_rancher2/auth_config_generic_oidc.py
pulumi_rancher2/auth_config_github.py
pulumi_rancher2/auth_config_githubapp.py
pulumi_rancher2/auth_config_keycloak.py
pulumi_rancher2/auth_config_okta.py
pulumi_rancher2/auth_config_open_ldap.py
pulumi_rancher2/auth_config_ping.py
pulumi_rancher2/bootstrap.py
pulumi_rancher2/catalog_v2.py
pulumi_rancher2/certificate.py
pulumi_rancher2/cloud_credential.py
pulumi_rancher2/cluster.py
pulumi_rancher2/cluster_driver.py
pulumi_rancher2/cluster_proxy_config_v2.py
pulumi_rancher2/cluster_role_template_binding.py
pulumi_rancher2/cluster_sync.py
pulumi_rancher2/cluster_v2.py
pulumi_rancher2/config_map_v2.py
pulumi_rancher2/custom_user_token.py
pulumi_rancher2/feature.py
pulumi_rancher2/get_catalog_v2.py
pulumi_rancher2/get_certificate.py
pulumi_rancher2/get_cloud_credential.py
pulumi_rancher2/get_cluster.py
pulumi_rancher2/get_cluster_driver.py
pulumi_rancher2/get_cluster_proxy_config_v2.py
pulumi_rancher2/get_cluster_role_template_binding.py
pulumi_rancher2/get_cluster_v2.py
pulumi_rancher2/get_config_map_v2.py
pulumi_rancher2/get_global_role.py
pulumi_rancher2/get_global_role_binding.py
pulumi_rancher2/get_namespace.py
pulumi_rancher2/get_node_driver.py
pulumi_rancher2/get_node_pool.py
pulumi_rancher2/get_pod_security_admission_configuration_template.py
pulumi_rancher2/get_principal.py
pulumi_rancher2/get_project.py
pulumi_rancher2/get_project_role_template_binding.py
pulumi_rancher2/get_registry.py
pulumi_rancher2/get_role_template.py
pulumi_rancher2/get_secret.py
pulumi_rancher2/get_secret_v2.py
pulumi_rancher2/get_setting.py
pulumi_rancher2/get_storage_class_v2.py
pulumi_rancher2/get_user.py
pulumi_rancher2/global_role.py
pulumi_rancher2-11.0.0.dist-info/METADATA
pulumi_rancher2-11.0.0.dist-info/WHEEL
pulumi_rancher2-11.0.0.dist-info/top_level.txt
pulumi_rancher2-11.0.0.dist-info/RECORD
