Metadata-Version: 2.4
Name: pulumi_rancher2
Version: 11.0.0
Summary: A Pulumi package for creating and managing rancher2 resources.
License: Apache-2.0
Project-URL: Homepage, https://pulumi.io
Project-URL: Repository, https://github.com/pulumi/pulumi-rancher2
Keywords: pulumi,rancher2
Requires-Python: >=3.9
Requires-Dist: parver>=0.2.1
Requires-Dist: pulumi<4.0.0,>=3.165.0
Requires-Dist: semver>=2.8.1
Requires-Dist: typing-extensions<5,>=4.11; python_version < "3.11"
